MANIFEST.in
jnius_config.py
setup.py
jnius/__init__.py
jnius/jni.pxi
jnius/jnius.pyx
jnius/jnius_conversion.pxi
jnius/jnius_env.pxi
jnius/jnius_export_class.pxi
jnius/jnius_export_func.pxi
jnius/jnius_jvm_android.pxi
jnius/jnius_jvm_desktop.pxi
jnius/jnius_jvm_dlopen.pxi
jnius/jnius_localref.pxi
jnius/jnius_nativetypes.pxi
jnius/jnius_nativetypes3.pxi
jnius/jnius_proxy.pxi
jnius/jnius_utils.pxi
jnius/reflect.py
jnius/signatures.py
jnius_indra.egg-info/PKG-INFO
jnius_indra.egg-info/SOURCES.txt
jnius_indra.egg-info/dependency_links.txt
jnius_indra.egg-info/requires.txt
jnius_indra.egg-info/top_level.txt